Workbook

Sheet Instructions
A1: GFC (Global Finance Corps) 10-K Data Extraction & Analysis Workbook
A3: Purpose
A4: This workbook holds cleaned, ratio-enriched financial data extracted from the 10-K filings
A5: of Microsoft, Tesla, and Apple (FY2023-FY2025). It feeds the AI chatbot's financial analysis.
A7: How to read this workbook
A8: - 'Raw Data' tab: one row per company-fiscal year. Blue text = figures pulled directly from
A9: the 10-K (hardcoded inputs, with source noted in the last column). Black text = formulas.
A10: - 'Ratios' tab: pulls from Raw Data automatically and computes the full ratio set per row.
A12: Workflow to complete the remaining 8 company-years
A13: 1. Open the 10-K on SEC EDGAR (Item 7 = MD&A narrative, Item 8 = financial statements).
A14: 2. Pull the figures listed in columns C through T of 'Raw Data' for that company/year.
A15: 3. Paste them into the matching blue input cells - do not touch the black formula cells.
... A20: Apple: FY2023, FY2024, FY2025 | Microsoft: FY2023, FY2024, FY2025 | Tesla: FY2023, FY2024, FY2025

Sheet Raw Data
A1: Company | B1: FiscalYear | C1: Reporting Date | D1: Revenue ($mm) | E1: GrossProfit ($mm) | F1: R&D Expense ($mm) | G1: SG&A Expense ($mm) | H1: Total OpEx ($mm) | I1: Operating Income ($mm) | J1: Net Income ($mm) | K1: Diluted EPS ($) | L1: Cash & Equivalents ($mm) | M1: Total Current Assets ($mm) | N1: Total Assets ($mm) | O1: Total Current Liabilities ($mm) | P1: Total Liabilities ($mm) | Q1: Total Equity ($mm) | R1: Operating Cash Flow ($mm) | S1: CapEx ($mm) | T1: Prior Yr Revenue ($mm) | U1: Source / Notes
A2: Apple | B2: FY2023 | C2: 45199 | D2: 383285 | E2: 169148 | F2: 29915 | G2: 24932 | H2: 54847 | I2: 114301 | J2: 96995 | K2: 6.13 | L2: 29965 | M2: 143566 | N2: 352583 | O2: 145308 | P2: 290437 | Q2: 62146 | R2: 110543 | S2: 10959 | T2: 394328 | U2: Apple FY2023 10-K (SEC EDGAR, filed 2023-11-03), Items 7 & 8
A3: Apple | B3: FY2024 | C3: 45563 | D3: 391035 | E3: 180683 | F3: 31370 | G3: 26097 | H3: 57467 | I3: 123216 | J3: 93736 | K3: 6.08 | L3: 29943 | M3: 152987 | N3: 364980 | O3: 176392 | P3: 308030 | Q3: 56950 | R3: 118254 | S3: 9447 | T3: 383285 | U3: TODO: fill from 10-K (SEC EDGAR, filed 2024-08-0)2, Items 7 & 8
A4: Apple | B4: FY2025 | C4: 45927 | D4: 416161 | E4: 195201 | F4: 34550 | G4: 27601 | H4: 62151 | I4: 133050 | J4: 112010 | K4: 7.46 | L4: 35934 | M4: 147957 | N4: 359241 | O4: 165631 | P4: 285508 | Q4: 73733 | R4: 111482 | S4: 12715 | T4: 391035 | U4: TODO: fill from 10-K (SEC EDGAR, filed 2025-10-31), Items 7 & 8
A5: Microsoft | B5: FY2023 | C5: 45107 | D5: 211915 | E5: 146052 | F5: 27195 | G5: 30334 | H5: 57529 | I5: 88523 | J5: 72361 | K5: 9.68 | L5: 34704 | M5: 184257 | N5: 411976 | O5: 104149 | P5: 205753 | Q5: 206223 | R5: 87582 | S5: 28107 | T5: 198270 | U5: TODO: fill from 10-K (SEC EDGAR, filed 2023-07-27), Items 7 & 8
A6: Microsoft | B6: FY2024 | C6: 45473 | D6: 245122 | E6: 171008 | F6: 29510 | G6: 31525 | H6: 61035 | I6: 109433 | J6: 88136 | K6: 12 | L6: 18315 | M6: 159734 | N6: 512163 | O6: 125286 | P6: 243686 | Q6: 268477 | R6: 118548 | S6: 44477 | T6: 211915 | U6: TODO: fill from 10-K (SEC EDGAR, filed 2027-07-30), Items 7 & 8
A7: Microsoft | B7: FY2025 | C7: 45838 | D7: 281724 | E7: 193893 | F7: 32488 | G7: 32877 | H7: 65365 | I7: 128528 | J7: 101832 | K7: 14 | L7: 30242 | M7: 191131 | N7: 619003 | O7: 141218 | P7: 275524 | Q7: 343479 | R7: 136162 | S7: 64551 | T7: 245122 | U7: TODO: fill from 10-K (SEC EDGAR, filed 2025-07-30), Items 7 & 8
A8: Tesla | B8: FY2023 | C8: 45291 | D8: 96773 | E8: 17660 | F8: 3969 | G8: 4800 | H8: 8769 | I8: 8891 | J8: 14974 | K8: 4.3 | L8: 16398 | M8: 49616 | N8: 106618 | O8: 28748 | P8: 43009 | Q8: 62634 | R8: 13256 | S8: 8898 | T8: 81462 | U8: TODO: fill from 10-K (SEC EDGAR, filed 2024-01-29, Items 7 & 8
A9: Tesla | B9: FY2024 | C9: 45657 | D9: 97690 | E9: 17450 | F9: 4540 | G9: 5150 | H9: 10374 | I9: 7076 | J9: 7153 | K9: 2.04 | L9: 16139 | M9: 58360 | N9: 122070 | O9: 28821 | P9: 48390 | Q9: 72913 | R9: 14923 | S9: 11342 | T9: 96773 | U9: TODO: fill from 10-K (SEC EDGAR, filed 2025-01-30, Items 7 & 8
A10: Tesla | B10: FY2025 | C10: 46022 | D10: 94827 | E10: 17094 | F10: 6411 | G10: 5834 | H10: 12739 | I10: 4355 | J10: 3855 | K10: 1.08 | L10: 16513 | M10: 68642 | N10: 137806 | O10: 31714 | P10: 54941 | Q10: 82137 | R10: 14747 | S10: 8527 | T10: 97690 | U10: TODO: fill from 10-K (SEC EDGAR, filed 2026-01-29, Items 7 & 8

Sheet Ratios
A1: Company | B1: FiscalYear | C1: Gross Margin % | D1: Operating Margin % | E1: Net Margin % | F1: ROE % | G1: ROA % | H1: Current Ratio | I1: Debt-to-Equity | J1: Free Cash Flow ($mm) | K1: Revenue Growth % (YoY)
A2: ='Raw Data'!A2 -> Apple | B2: ='Raw Data'!B2 -> FY2023 | C2: =IFERROR('Raw Data'!E2/'Raw Data'!D2,"") -> 0.4413113 | D2: =IFERROR('Raw Data'!I2/'Raw Data'!D2,"") -> 0.29821412 | E2: =IFERROR('Raw Data'!J2/'Raw Data'!D2,"") -> 0.25306234 | F2: =IFERROR('Raw Data'!J2/'Raw Data'!Q2,"") -> 1.5607601 | G2: =IFERROR('Raw Data'!J2/'Raw Data'!N2,"") -> 0.27509835 | H2: =IFERROR('Raw Data'!M2/'Raw Data'!O2,"") -> 0.98801167 | I2: =IFERROR('Raw Data'!P2/'Raw Data'!Q2,"") -> 4.6734625 | J2: =IFERROR('Raw Data'!R2-'Raw Data'!S2,"") -> 99584 | K2: =IFERROR(('Raw Data'!D2-'Raw Data'!T2)/'Raw Data'!T2,"") -> -0.028004605
A3: ='Raw Data'!A3 -> Apple | B3: ='Raw Data'!B3 -> FY2024 | C3: =IFERROR('Raw Data'!E3/'Raw Data'!D3,"") -> 0.4620635 | D3: =IFERROR('Raw Data'!I3/'Raw Data'!D3,"") -> 0.31510223 | E3: =IFERROR('Raw Data'!J3/'Raw Data'!D3,"") -> 0.23971256 | F3: =IFERROR('Raw Data'!J3/'Raw Data'!Q3,"") -> 1.645935 | G3: =IFERROR('Raw Data'!J3/'Raw Data'!N3,"") -> 0.25682503 | H3: =IFERROR('Raw Data'!M3/'Raw Data'!O3,"") -> 0.86731258 | I3: =IFERROR('Raw Data'!P3/'Raw Data'!Q3,"") -> 5.4087796 | J3: =IFERROR('Raw Data'!R3-'Raw Data'!S3,"") -> 108807 | K3: =IFERROR(('Raw Data'!D3-'Raw Data'!T3)/'Raw Data'!T3,"") -> 0.020219941
A4: ='Raw Data'!A4 -> Apple | B4: ='Raw Data'!B4 -> FY2025 | C4: =IFERROR('Raw Data'!E4/'Raw Data'!D4,"") -> 0.46905164 | D4: =IFERROR('Raw Data'!I4/'Raw Data'!D4,"") -> 0.319708 | E4: =IFERROR('Raw Data'!J4/'Raw Data'!D4,"") -> 0.26915064 | F4: =IFERROR('Raw Data'!J4/'Raw Data'!Q4,"") -> 1.5191298 | G4: =IFERROR('Raw Data'!J4/'Raw Data'!N4,"") -> 0.31179626 | H4: =IFERROR('Raw Data'!M4/'Raw Data'!O4,"") -> 0.89329292 | I4: =IFERROR('Raw Data'!P4/'Raw Data'!Q4,"") -> 3.8721875 | J4: =IFERROR('Raw Data'!R4-'Raw Data'!S4,"") -> 98767 | K4: =IFERROR(('Raw Data'!D4-'Raw Data'!T4)/'Raw Data'!T4,"") -> 0.064255118
A5: ='Raw Data'!A5 -> Microsoft | B5: ='Raw Data'!B5 -> FY2023 | C5: =IFERROR('Raw Data'!E5/'Raw Data'!D5,"") -> 0.68920086 | D5: =IFERROR('Raw Data'!I5/'Raw Data'!D5,"") -> 0.41772881 | E5: =IFERROR('Raw Data'!J5/'Raw Data'!D5,"") -> 0.34146238 | F5: =IFERROR('Raw Data'!J5/'Raw Data'!Q5,"") -> 0.35088715 | G5: =IFERROR('Raw Data'!J5/'Raw Data'!N5,"") -> 0.17564373 | H5: =IFERROR('Raw Data'!M5/'Raw Data'!O5,"") -> 1.7691673 | I5: =IFERROR('Raw Data'!P5/'Raw Data'!Q5,"") -> 0.99772091 | J5: =IFERROR('Raw Data'!R5-'Raw Data'!S5,"") -> 59475 | K5: =IFERROR(('Raw Data'!D5-'Raw Data'!T5)/'Raw Data'!T5,"") -> 0.068820296
A6: ='Raw Data'!A6 -> Microsoft | B6: ='Raw Data'!B6 -> FY2024 | C6: =IFERROR('Raw Data'!E6/'Raw Data'!D6,"") -> 0.69764444 | D6: =IFERROR('Raw Data'!I6/'Raw Data'!D6,"") -> 0.446443 | E6: =IFERROR('Raw Data'!J6/'Raw Data'!D6,"") -> 0.35955973 | F6: =IFERROR('Raw Data'!J6/'Raw Data'!Q6,"") -> 0.32828138 | G6: =IFERROR('Raw Data'!J6/'Raw Data'!N6,"") -> 0.17208584 | H6: =IFERROR('Raw Data'!M6/'Raw Data'!O6,"") -> 1.2749549 | I6: =IFERROR('Raw Data'!P6/'Raw Data'!Q6,"") -> 0.90766062 | J6: =IFERROR('Raw Data'!R6-'Raw Data'!S6,"") -> 74071 | K6: =IFERROR(('Raw Data'!D6-'Raw Data'!T6)/'Raw Data'!T6,"") -> 0.15669962
A7: ='Raw Data'!A7 -> Microsoft | B7: ='Raw Data'!B7 -> FY2025 | C7: =IFERROR('Raw Data'!E7/'Raw Data'!D7,"") -> 0.68823742 | D7: =IFERROR('Raw Data'!I7/'Raw Data'!D7,"") -> 0.45621956 | E7: =IFERROR('Raw Data'!J7/'Raw Data'!D7,"") -> 0.36146015 | F7: =IFERROR('Raw Data'!J7/'Raw Data'!Q7,"") -> 0.29647227 | G7: =IFERROR('Raw Data'!J7/'Raw Data'!N7,"") -> 0.1645097 | H7: =IFERROR('Raw Data'!M7/'Raw Data'!O7,"") -> 1.3534464 | I7: =IFERROR('Raw Data'!P7/'Raw Data'!Q7,"") -> 0.80215675 | J7: =IFERROR('Raw Data'!R7-'Raw Data'!S7,"") -> 71611 | K7: =IFERROR(('Raw Data'!D7-'Raw Data'!T7)/'Raw Data'!T7,"") -> 0.14932156
A8: ='Raw Data'!A8 -> Tesla | B8: ='Raw Data'!B8 -> FY2023 | C8: =IFERROR('Raw Data'!E8/'Raw Data'!D8,"") -> 0.18248892 | D8: =IFERROR('Raw Data'!I8/'Raw Data'!D8,"") -> 0.0918748 | E8: =IFERROR('Raw Data'!J8/'Raw Data'!D8,"") -> 0.15473324 | F8: =IFERROR('Raw Data'!J8/'Raw Data'!Q8,"") -> 0.23907143 | G8: =IFERROR('Raw Data'!J8/'Raw Data'!N8,"") -> 0.14044533 | H8: =IFERROR('Raw Data'!M8/'Raw Data'!O8,"") -> 1.725894 | I8: =IFERROR('Raw Data'!P8/'Raw Data'!Q8,"") -> 0.68667178 | J8: =IFERROR('Raw Data'!R8-'Raw Data'!S8,"") -> 4358 | K8: =IFERROR(('Raw Data'!D8-'Raw Data'!T8)/'Raw Data'!T8,"") -> 0.18795267
A9: ='Raw Data'!A9 -> Tesla | B9: ='Raw Data'!B9 -> FY2024 | C9: =IFERROR('Raw Data'!E9/'Raw Data'!D9,"") -> 0.17862627 | D9: =IFERROR('Raw Data'!I9/'Raw Data'!D9,"") -> 0.072433207 | E9: =IFERROR('Raw Data'!J9/'Raw Data'!D9,"") -> 0.073221415 | F9: =IFERROR('Raw Data'!J9/'Raw Data'!Q9,"") -> 0.098103219 | G9: =IFERROR('Raw Data'!J9/'Raw Data'!N9,"") -> 0.058597526 | H9: =IFERROR('Raw Data'!M9/'Raw Data'!O9,"") -> 2.0249124 | I9: =IFERROR('Raw Data'!P9/'Raw Data'!Q9,"") -> 0.66366766 | J9: =IFERROR('Raw Data'!R9-'Raw Data'!S9,"") -> 3581 | K9: =IFERROR(('Raw Data'!D9-'Raw Data'!T9)/'Raw Data'!T9,"") -> 0.0094757835
A10: ='Raw Data'!A10 -> Tesla | B10: ='Raw Data'!B10 -> FY2025 | C10: =IFERROR('Raw Data'!E10/'Raw Data'!D10,"") -> 0.18026511 | D10: =IFERROR('Raw Data'!I10/'Raw Data'!D10,"") -> 0.045925738 | E10: =IFERROR('Raw Data'!J10/'Raw Data'!D10,"") -> 0.040652979 | F10: =IFERROR('Raw Data'!J10/'Raw Data'!Q10,"") -> 0.046933781 | G10: =IFERROR('Raw Data'!J10/'Raw Data'!N10,"") -> 0.027974109 | H10: =IFERROR('Raw Data'!M10/'Raw Data'!O10,"") -> 2.1644069 | I10: =IFERROR('Raw Data'!P10/'Raw Data'!Q10,"") -> 0.66889465 | J10: =IFERROR('Raw Data'!R10-'Raw Data'!S10,"") -> 6220 | K10: =IFERROR(('Raw Data'!D10-'Raw Data'!T10)/'Raw Data'!T10,"") -> -0.029306992
A13: All ratios computed via formula from 'Raw Data'. Blank until that row's inputs are filled in.
